CHANGES.rst
MANIFEST.in
README.rst
setup.cfg
setup.py
collective/__init__.py
collective.auditlog.egg-info/PKG-INFO
collective.auditlog.egg-info/SOURCES.txt
collective.auditlog.egg-info/dependency_links.txt
collective.auditlog.egg-info/entry_points.txt
collective.auditlog.egg-info/namespace_packages.txt
collective.auditlog.egg-info/not-zip-safe
collective.auditlog.egg-info/requires.txt
collective.auditlog.egg-info/top_level.txt
collective/auditlog/__init__.py
collective/auditlog/action.py
collective/auditlog/action.zcml
collective/auditlog/asyncqueue.py
collective/auditlog/browser.py
collective/auditlog/catalog.py
collective/auditlog/configure.zcml
collective/auditlog/controlpanel.pt
collective/auditlog/controlpanel.py
collective/auditlog/db.py
collective/auditlog/handlers.py
collective/auditlog/interfaces.py
collective/auditlog/logview.pt
collective/auditlog/models.py
collective/auditlog/permissions.py
collective/auditlog/permissions.zcml
collective/auditlog/profiles.zcml
collective/auditlog/tasks.py
collective/auditlog/td.py
collective/auditlog/testing.py
collective/auditlog/utils.py
collective/auditlog/locales/collective.auditlog.pot
collective/auditlog/profiles/default/actions.xml
collective/auditlog/profiles/default/contentrules.xml
collective/auditlog/profiles/default/controlpanel.xml
collective/auditlog/profiles/default/metadata.xml
collective/auditlog/profiles/default/registry.xml
collective/auditlog/profiles/default/rolemap.xml
collective/auditlog/profiles/default/toolset.xml
collective/auditlog/static/infinitescroll.jquery.js
collective/auditlog/tests/__init__.py
collective/auditlog/tests/test_actions.py
collective/auditlog/upgrades/__init__.py
collective/auditlog/upgrades/configure.zcml
collective/auditlog/upgrades/to1001.py
docs/INSTALL.txt
docs/LICENSE.GPL
docs/LICENSE.txt