Metadata-Version: 2.1
Name: collective.auditlog
Version: 2.0.0
Summary: Provides extra conditions and triggers for all content actions
Home-page: http://svn.plone.org/svn/collective/
Author: rain2o
Author-email: Joel@rain2odesigns.com
License: GPL
Keywords: Plone Audit Log
Classifier: Framework :: Plone
Classifier: Framework :: Plone :: 5.1
Classifier: Framework :: Plone :: 5.2
Classifier: Framework :: Plone :: Addon
Classifier: Programming Language :: Python
Classifier: Programming Language :: Python :: 2.7
Classifier: Programming Language :: Python :: 3.7
Classifier: Operating System :: OS Independent
Provides-Extra: celery
Provides-Extra: test
